rivet_browse/__init__.py
rivet_browse-0.0.1.dist-info/LICENSE
rivet_browse-0.0.1.dist-info/METADATA
rivet_browse-0.0.1.dist-info/WHEEL
rivet_browse-0.0.1.dist-info/entry_points.txt
rivet_browse-0.0.1.dist-info/RECORD
