Metadata-Version: 2.1
Name: rivet-browse
Version: 0.0.1
Summary: 
Author: Alexander Puck Neuwirth
Author-email: alexander@neuwirth-informatik.de
Requires-Python: >=3.11,<4.0
Classifier: Programming Language :: Python :: 3
Classifier: Programming Language :: Python :: 3.11
Classifier: Programming Language :: Python :: 3.12
Requires-Dist: matplotlib
